rpmlint_codeclimate/__init__.py
rpmlint_codeclimate/__main__.py
rpmlint_codeclimate/_version.py
rpmlint_codeclimate/parser.py
rpmlint_codeclimate/tests/__init__.py
rpmlint_codeclimate/tests/example.spec
rpmlint_codeclimate/tests/test_parser.py
rpmlint_codeclimate-0.2.1.dist-info/LICENSE
rpmlint_codeclimate-0.2.1.dist-info/METADATA
rpmlint_codeclimate-0.2.1.dist-info/WHEEL
rpmlint_codeclimate-0.2.1.dist-info/top_level.txt
rpmlint_codeclimate-0.2.1.dist-info/RECORD
